ionos_api/Client.py
ionos_api/Config.py
ionos_api/HTTPSession.py
ionos_api/__init__.py
ionos_api/Model/Record.py
ionos_api/Model/Zone.py
ionos_api/Model/__init__.py
ionos_api-0.1.data/data/ionos_api/whl.requirements.txt
ionos_api-0.1.dist-info/METADATA
ionos_api-0.1.dist-info/WHEEL
ionos_api-0.1.dist-info/top_level.txt
ionos_api-0.1.dist-info/RECORD
