Metadata-Version: 2.1
Name: ionos-api
Version: 0.1
Summary: Client for the ionos DNS API.
Home-page: https://gitlab.com/todo
Author: Axel Paccalin
Author-email: axel.paccalin@enno.ai
Project-URL: Bug Tracker, https://gitlab.com/todo/issues
Classifier: Programming Language :: Python :: 3
Classifier: Operating System :: OS Independent
Requires-Python: >=3.10
Requires-Dist: requests
